watanlib1/__init__.py
watanlib1-0.1.0.dist-info/licenses/LICENSE.txt
watanlib1-0.1.0.dist-info/METADATA
watanlib1-0.1.0.dist-info/WHEEL
watanlib1-0.1.0.dist-info/top_level.txt
watanlib1-0.1.0.dist-info/RECORD
